{
  "data": [
    {
      "title": "Покушать и выпить чаю",
      "description": "Съешь ещё этих мягких французских булок, да выпей [же] чаю. 1234567890."
    },
    {
      "title": "Селфи в самолете",
      "description": "Аэрофотосъёмка ландшафта уже выявила земли богачей и процветающих крестьян."
    },
    {
      "title": "Директор обжора",
      "description": "Юный директор целиком сжевал весь объём продукции фундука (товара дефицитного и деликатесного), идя энергично через хрустящий камыш."
    },
    {
      "title": "Передатчик",
      "description": "Безмозглый широковещательный цифровой передатчик сужающихся экспонент."
    },
    {
      "title": "Верблюд и шиповник",
      "description": "Флегматичная эта верблюдица жует у подъезда засыхающий горький шиповник."
    }
  ]
}
